LICENSE
MANIFEST.in
README.rst
requirements.txt
setup.cfg
setup.py
./operalib/__init__.py
./operalib/kernel_maps.py
./operalib/kernels.py
./operalib/learningrate.py
./operalib/metrics.py
./operalib/onorma.py
./operalib/orff.py
./operalib/quantile.py
./operalib/ridge.py
./operalib/risk.py
./operalib/signal.py
./operalib/datasets/__init__.py
./operalib/datasets/awful.py
./operalib/datasets/quantile.py
./operalib/datasets/structure.py
./operalib/datasets/vectorfield.py
./operalib/preprocessing/__init__.py
./operalib/preprocessing/simplex.py
./operalib/tests/__init__.py
./operalib/tests/test_KernelRidge_cdf.py
./operalib/tests/test_KernelRidge_dec.py
./operalib/tests/test_QuantileRegression.py
./operalib/tests/test_awful.py
./operalib/tests/test_learningrate.py
./operalib/tests/test_metrics.py
./operalib/tests/test_onorma.py
./operalib/tests/test_risk.py
./operalib/tests/test_semisup.py
./operalib/tests/test_simplex_coding.py
doc/Makefile
doc/api.rst
doc/conf.py
doc/contact.rst
doc/index.rst
doc/make.bat
doc/ridge.rst
doc/modules/datasets.rst
doc/modules/kernels.rst
doc/modules/learningrate.rst
doc/modules/metrics.rst
doc/modules/onorma.rst
doc/modules/quantile.rst
doc/modules/ridge.rst
doc/modules/risk.rst
doc/modules/signal.rst
doc/reference_papers/index.rst
examples/README.txt
examples/plot_ovk_onorma.py
examples/plot_ovk_quantile_regression.py
examples/plot_ovk_regression_cf.py
examples/plot_ovk_regression_cf_semisup.py
examples/plot_ovk_regression_multiple_outputs.py
examples/plot_ovk_sparse_quantile_regression.py
operalib.egg-info/PKG-INFO
operalib.egg-info/SOURCES.txt
operalib.egg-info/dependency_links.txt
operalib.egg-info/not-zip-safe
operalib.egg-info/requires.txt
operalib.egg-info/top_level.txt