Metadata-Version: 1.1
Name: operalib
Version: 0.2b27
Summary: A python module for learnign with operator-valued kernels
Home-page: http://operalib.github.io/operalib/documentation/
Author: Romain Brault
Author-email: romain.brault@telecom-paristech.fr
License: MIT
Download-URL: https://github.com/operalib/operalib/
Platform: UNKNOWN
Classifier: Intended Audience :: Science/Research
Classifier: Intended Audience :: Developers
Classifier: License :: OSI Approved
Classifier: Programming Language :: C
Classifier: Programming Language :: Python
Classifier: Topic :: Software Development
Classifier: Topic :: Scientific/Engineering
Classifier: Operating System :: Microsoft :: Windows
Classifier: Operating System :: POSIX
Classifier: Operating System :: Unix
Classifier: Operating System :: MacOS
Classifier: Programming Language :: Python :: 2
Classifier: Programming Language :: Python :: 2.7
Classifier: Programming Language :: Python :: 3
Classifier: Programming Language :: Python :: 3.5
